mdgutil/__init__.py
mdgutil/general.py
mdgutil-0.0.2.dist-info/METADATA
mdgutil-0.0.2.dist-info/WHEEL
mdgutil-0.0.2.dist-info/licenses/LICENSE
mdgutil-0.0.2.dist-info/RECORD
